examples/test_nested_example.py
examples/test_multiple_children_example.py
examples/test_hamcrest_example.py
examples/__init__.py
snakespec-0.1.2.dist-info/METADATA
snakespec-0.1.2.dist-info/WHEEL
snakespec-0.1.2.dist-info/top_level.txt
snakespec-0.1.2.dist-info/RECORD
snakespec-0.1.2.dist-info/metadata.json
snakespec-0.1.2.dist-info/entry_points.txt
snakespec-0.1.2.dist-info/DESCRIPTION.rst
snakespec/snakespec.py
snakespec/__init__.py
