Metadata-Version: 2.0
Name: snakespec
Version: 0.1.2
Summary: BDD testing for python
Home-page: https://github.com/iredelmeier/snakespec
Author: Isobel Redelmeier
Author-email: iredelmeier@gmail.com
License: MIT
Keywords: test nosetests nose nosetest tdd bdd testing rspec
Platform: UNKNOWN
Classifier: Development Status :: 3 - Alpha
Classifier: Intended Audience :: Developers
Classifier: Topic :: Software Development :: Testing
Classifier: License :: OSI Approved :: MIT License
Classifier: Programming Language :: Python :: 2.7
Classifier: Operating System :: OS Independent
Requires-Dist: nose
